macrostrat/auth_system/__init__.py
macrostrat/auth_system/core/__init__.py
macrostrat/auth_system/core/database.py
macrostrat/auth_system/core/main.py
macrostrat/auth_system/core/model.py
macrostrat/auth_system/core/schema.py
macrostrat/auth_system/legacy/__init__.py
macrostrat/auth_system/legacy/api.py
macrostrat/auth_system/legacy/backend.py
macrostrat/auth_system/legacy/context.py
macrostrat/auth_system/legacy/identity.py
macrostrat/auth_system/legacy/test_auth.py
macrostrat_auth_system-1.0.3.dist-info/METADATA
macrostrat_auth_system-1.0.3.dist-info/WHEEL
macrostrat_auth_system-1.0.3.dist-info/RECORD
