Metadata-Version: 2.1
Name: macrostrat.auth_system
Version: 1.0.3
Summary: Authentication system for Macrostrat and related apps
Author: Daven Quinn
Author-email: code@davenquinn.com
Requires-Python: >=3.10,<4.0
Classifier: Programming Language :: Python :: 3
Classifier: Programming Language :: Python :: 3.10
Classifier: Programming Language :: Python :: 3.11
Classifier: Programming Language :: Python :: 3.12
Requires-Dist: PyJWT (>=1.7.1,<3.0)
Requires-Dist: bcrypt (>=4.1.1,<5.0.0)
Requires-Dist: fastapi (>=0.104.0,<0.105.0)
Requires-Dist: httpx (>=0.25.0,<0.26.0)
Requires-Dist: macrostrat.database (>=3.3.1,<4.0.0)
Requires-Dist: macrostrat.utils (>=1.2.0,<2.0.0)
Requires-Dist: python-jose[cryptography] (>=3.3.0,<4.0.0)
Requires-Dist: starlette (>=0.27.0,<0.28.0)
Requires-Dist: webargs-starlette (>=2.0.0,<3.0.0)
Requires-Dist: werkzeug (>=2.3.7,<4.0)
